odoo_runner.py
odoo_runner-0.0.3.dist-info/LICENSE
odoo_runner-0.0.3.dist-info/METADATA
odoo_runner-0.0.3.dist-info/WHEEL
odoo_runner-0.0.3.dist-info/top_level.txt
odoo_runner-0.0.3.dist-info/RECORD
