Metadata-Version: 2.1
Name: odoo-runner
Version: 0.0.3
Summary: Simple wrapper for running headless Odoo scripts
Author-email: "Janos Gerzson (@grzs)" <gerzsonj@gmail.com>
License: GNU GENERAL PUBLIC LICENSE
Project-URL: homepage, https://github.com/korallit/odoo-runner
Keywords: odoo
License-File: LICENSE
